imctermite.cp39-win_amd64.pyd
imctermite-2.1.18.dist-info/LICENSE
imctermite-2.1.18.dist-info/METADATA
imctermite-2.1.18.dist-info/WHEEL
imctermite-2.1.18.dist-info/top_level.txt
imctermite-2.1.18.dist-info/RECORD
