Metadata-Version: 2.1
Name: imctermite
Version: 2.1.18
Summary: Enables extraction of measurement data from binary files with extension 'raw' used by proprietary software imcFAMOS and imcSTUDIO and facilitates its storage in open source file formats
Home-page: https://github.com/RecordEvolution/IMCtermite.git
Author: Record Evolution GmbH
Author-email: mario.fink@record-evolution.de
Maintainer: Record Evolution GmbH
License: MIT License
Keywords: IMC,raw,imcFAMOS,imcSTUDIO,imcCRONOS
Platform: UNKNOWN
Classifier: Programming Language :: Python :: 3
Classifier: License :: OSI Approved :: MIT License
Classifier: Operating System :: OS Independent
Classifier: Topic :: Scientific/Engineering
Classifier: Topic :: Software Development :: Libraries :: Python Modules
License-File: LICENSE
